vite_to_flask/__init__.py
vite_to_flask/_html_tags.py
vite_to_flask/flask_extension.py
vite_to_flask/helpers.py
vite_to_flask/parser.py
vite_to_flask-0.7.1.dist-info/entry_points.txt
vite_to_flask-0.7.1.dist-info/LICENSE
vite_to_flask-0.7.1.dist-info/WHEEL
vite_to_flask-0.7.1.dist-info/METADATA
vite_to_flask-0.7.1.dist-info/RECORD
