Metadata-Version: 2.1
Name: vite-to-flask
Version: 0.7.1
Summary: Transport Vite apps to Flask / Flask blueprints.
Author-email: David Carmichael <david@uilix.com>
Requires-Python: >=3.8
Classifier: Programming Language :: Python :: 3.8
Classifier: Programming Language :: Python :: 3.9
Classifier: Programming Language :: Python :: 3.10
Classifier: Programming Language :: Python :: 3.11
Classifier: Programming Language :: Python :: 3.12
Classifier: Topic :: Internet :: WWW/HTTP :: Dynamic Content
Classifier: Natural Language :: English
Requires-Dist: flask
